mango_explorer_v4/__init__.py
mango_explorer_v4/accounts/__init__.py
mango_explorer_v4/accounts/bank.py
mango_explorer_v4/accounts/book_side.py
mango_explorer_v4/accounts/event_queue.py
mango_explorer_v4/accounts/group.py
mango_explorer_v4/accounts/mango_account.py
mango_explorer_v4/accounts/mint_info.py
mango_explorer_v4/accounts/perp_market.py
mango_explorer_v4/accounts/serum3_market.py
mango_explorer_v4/accounts/serum3_market_index_reservation.py
mango_explorer_v4/accounts/stub_oracle.py
mango_explorer_v4/constants.py
mango_explorer_v4/constructs/book_side_items.py
mango_explorer_v4/constructs/serum3_reserved.py
mango_explorer_v4/errors/__init__.py
mango_explorer_v4/errors/anchor.py
mango_explorer_v4/errors/custom.py
mango_explorer_v4/examples/atomic_cancel_replace.py
mango_explorer_v4/examples/balances.py
mango_explorer_v4/examples/cancel_all_orders.py
mango_explorer_v4/examples/equity.py
mango_explorer_v4/examples/fills.py
mango_explorer_v4/examples/funding_rate.py
mango_explorer_v4/examples/get_all_mango_accounts.py
mango_explorer_v4/examples/health_ratio.py
mango_explorer_v4/examples/incremental_fills.py
mango_explorer_v4/examples/incremental_orderbook_l2.py
mango_explorer_v4/examples/market_maker.py
mango_explorer_v4/examples/orderbook_l2.py
mango_explorer_v4/examples/orderbook_l3.py
mango_explorer_v4/examples/orders.py
mango_explorer_v4/examples/place_order.py
mango_explorer_v4/examples/place_perp_pegged_order.py
mango_explorer_v4/examples/positions.py
mango_explorer_v4/examples/scratch.py
mango_explorer_v4/examples/symbols.py
mango_explorer_v4/helpers/bank.py
mango_explorer_v4/helpers/health_cache.py
mango_explorer_v4/helpers/i80f48.py
mango_explorer_v4/helpers/mango_account.py
mango_explorer_v4/helpers/perp_info.py
mango_explorer_v4/helpers/perp_market.py
mango_explorer_v4/helpers/perp_open_order.py
mango_explorer_v4/helpers/perp_position.py
mango_explorer_v4/helpers/prices.py
mango_explorer_v4/helpers/serum3_info.py
mango_explorer_v4-0.8.2.dist-info/METADATA
mango_explorer_v4-0.8.2.dist-info/WHEEL
mango_explorer_v4-0.8.2.dist-info/RECORD
